MontyCarlo/DATA_STATUS.txt
MontyCarlo/__init__.pxd
MontyCarlo/__init__.py
MontyCarlo/_init.cpp
MontyCarlo/_init.cpython-37m-darwin.so
MontyCarlo/_init.pxd
MontyCarlo/_init.pyx
MontyCarlo/install.py
MontyCarlo/plotter.py
MontyCarlo/settings.py
MontyCarlo/setup.py
MontyCarlo/sources.cpp
MontyCarlo/sources.cpython-37m-darwin.so
MontyCarlo/sources.pyx
MontyCarlo/types.cpp
MontyCarlo/types.cpython-37m-darwin.so
MontyCarlo/types.pxd
MontyCarlo/types.pyx
MontyCarlo/external/README.md
MontyCarlo/external/__init__.pxd
MontyCarlo/external/__init__.py
MontyCarlo/external/mixmax_interface.cpp
MontyCarlo/external/mixmax_interface.cpython-37m-darwin.so
MontyCarlo/external/mixmax_interface.pxd
MontyCarlo/external/mixmax_interface.pyx
MontyCarlo/external/htmlcreator/__init__.py
MontyCarlo/external/htmlcreator/css.py
MontyCarlo/external/htmlcreator/document.py
MontyCarlo/external/htmlcreator/__pycache__/__init__.cpython-38.pyc
MontyCarlo/external/htmlcreator/__pycache__/css.cpython-38.pyc
MontyCarlo/external/htmlcreator/__pycache__/document.cpython-38.pyc
MontyCarlo/external/mixmax_release_200final/Makefile
MontyCarlo/external/mixmax_release_200final/N240_1200.out
MontyCarlo/external/mixmax_release_200final/README.pdf
MontyCarlo/external/mixmax_release_200final/driver_gsl.c
MontyCarlo/external/mixmax_release_200final/driver_iotest.c
MontyCarlo/external/mixmax_release_200final/driver_main.c
MontyCarlo/external/mixmax_release_200final/driver_testU01.c
MontyCarlo/external/mixmax_release_200final/driver_threads.c
MontyCarlo/external/mixmax_release_200final/driver_time.c
MontyCarlo/external/mixmax_release_200final/driver_verification.c
MontyCarlo/external/mixmax_release_200final/example.cpp
MontyCarlo/external/mixmax_release_200final/mathematica.N240.txt
MontyCarlo/external/mixmax_release_200final/mixmax.c
MontyCarlo/external/mixmax_release_200final/mixmax.h
MontyCarlo/external/mixmax_release_200final/mixmax.hpp
MontyCarlo/external/mixmax_release_200final/mixmax.s
MontyCarlo-0.1a0.dev2.dist-info/LICENSE
MontyCarlo-0.1a0.dev2.dist-info/METADATA
MontyCarlo-0.1a0.dev2.dist-info/WHEEL
MontyCarlo-0.1a0.dev2.dist-info/top_level.txt
MontyCarlo-0.1a0.dev2.dist-info/RECORD
