Metadata-Version: 2.1
Name: MontyCarlo
Version: 0.1a0.dev2
Summary: A fast general purpose monte carlo particle simulator (photons, electrons and positrons). Written in Cython, Python and C++.
Home-page: https://github.com/RuiFilipeCampos/MontyCarlo
Author: Rui Filipe de Sousa Campos
Author-email: ruifilipedesousacampos@gmail.com
License: {file = "LICENSE"}
Project-URL: Bug Tracker, https://github.com/RuiFilipeCampos/MontyCarlo/issues
Platform: UNKNOWN
Classifier: Programming Language :: Python
Classifier: Programming Language :: Python :: 3
Classifier: Programming Language :: Python :: 3.7
Classifier: Programming Language :: Python :: 3.8
Classifier: Programming Language :: Python :: 3.9
Classifier: Programming Language :: Python :: 3 :: Only
Classifier: Programming Language :: Cython
Classifier: Programming Language :: C++
Classifier: Development Status :: 2 - Pre-Alpha
Classifier: Intended Audience :: Education
Classifier: Intended Audience :: Science/Research
Classifier: Intended Audience :: Developers
Classifier: Intended Audience :: Healthcare Industry
Classifier: Operating System :: Microsoft :: Windows
Classifier: Operating System :: MacOS
Classifier: Topic :: Scientific/Engineering
Classifier: Topic :: Scientific/Engineering :: Medical Science Apps.
Classifier: Topic :: Scientific/Engineering :: Physics
Classifier: Topic :: Scientific/Engineering :: Visualization
Requires-Python: >=3.6
Requires-Dist: requests
Requires-Dist: gdown
Requires-Dist: numpy
Requires-Dist: scipy
Requires-Dist: matplotlib
Requires-Dist: pyvista
Requires-Dist: numba
Requires-Dist: bs4
Requires-Dist: pandas
Requires-Dist: plotly
Requires-Dist: scikit-image
Requires-Dist: Jinja2
Requires-Dist: pyunpack
Requires-Dist: patool
